get_proxy.py
json_to_excel.py
main.py
proxy_url.py
fanatics_api-3.1.dist-info/METADATA
fanatics_api-3.1.dist-info/WHEEL
fanatics_api-3.1.dist-info/entry_points.txt
fanatics_api-3.1.dist-info/top_level.txt
fanatics_api-3.1.dist-info/RECORD
