Metadata-Version: 2.1
Name: fanatics-api
Version: 3.1
Summary: include to csv/excel
Author: Ruibin Zhang
Author-email: ruibin.zhang021@icloud.com
Requires-Dist: requests
